Workbook
Name AttendanceBase: #N/A
Name DateBase: #N/A
Name SessionBase: #N/A

Sheet Event Dashboard
A1: Tech Innovators Summit
A4: Event Dashboard
A6: Historical attendees | E6: Historical ticket revenue | I6: Average ticket price
A7: =SUM('Dashboard Data'!C6:C8) -> 100 | E7: =SUM('Dashboard Data'!B6:B8) -> 48300 | I7: =IF(A7=0,0,E7/A7) -> 483
A10: Planning attendance | E10: Forecast ticket revenue | I10: Forecast profit
A11: =Projections!B23 -> 60 | E11: =Projections!B24 -> 28980 | I11: =Projections!B27 -> 15680
A14: Marketing (EUR) | C14: =Projections!B25 -> 9000 | E14: Operations (EUR) | G14: =Projections!B26 -> 4300 | I14: Profit target (EUR) | L14: =Projections!B28 -> 45000
A16: Required price | C16: =Projections!B34 -> 971.66667 | E16: Minimum attendees | G16: =Projections!B38 -> 121 | I16: Current average price | L16: =Projections!B22 -> 483
A18: Filters below affect historical KPIs and all three charts. The forecast uses the full training history.

Sheet Assumptions
B1: Original budget (EUR) | E1: Budget Challenge (EUR)
B2: Target profit | C2: 45000 | E2: Target profit
B4: Marketing costs | C4: 9000 | E4: Marketing costs | F4: 10000
B6: Operational costs | C6: 4300 | E6: Operational costs | F6: 25000
B9: Source: original workbook, Assumptions!C2/C4/C6.
B10: Budget Challenge costs: assignment instructions.
B11: Target is written as “€100,00” in the assignment. Enter the confirmed amount in F2.
B13: All amounts are EUR. No exchange rate or sponsorship revenue is assumed.

Sheet Projections
A1: Attendance forecast and pricing
A5: Forecast month | B5: ETS registrations | C5: Planning attendees | D5: Revenue at historic price | F5: Forecast basis
A6: =EDATE('Monthly Summary'!$A$30,1) -> 45627 | B6: =_xlfn.FORECAST.ETS(A6,'Monthly Summary'!$B$7:$B$29,'Monthly Summary'!$A$7:$A$29,0,1,1) -> 5.0390426 | C6: =MAX(0,ROUND(B6,0)) -> 5 | D6: =C6*$B$22 -> 2415 | F6: 12 months after the final source month: Dec 2024–Nov 2025.
A7: =EDATE('Monthly Summary'!$A$30,2) -> 45658 | B7: =_xlfn.FORECAST.ETS(A7,'Monthly Summary'!$B$7:$B$29,'Monthly Summary'!$A$7:$A$29,0,1,1) -> 5.0801478 | C7: =MAX(0,ROUND(B7,0)) -> 5 | D7: =C7*$B$22 -> 2415
A8: =EDATE('Monthly Summary'!$A$30,3) -> 45689 | B8: =_xlfn.FORECAST.ETS(A8,'Monthly Summary'!$B$7:$B$29,'Monthly Summary'!$A$7:$A$29,0,1,1) -> 5.1212531 | C8: =MAX(0,ROUND(B8,0)) -> 5 | D8: =C8*$B$22 -> 2415 | F8: Training window
A9: =EDATE('Monthly Summary'!$A$30,4) -> 45717 | B9: =_xlfn.FORECAST.ETS(A9,'Monthly Summary'!$B$7:$B$29,'Monthly Summary'!$A$7:$A$29,0,1,1) -> 5.1623584 | C9: =MAX(0,ROUND(B9,0)) -> 5 | D9: =C9*$B$22 -> 2415 | F9: Dec 2022–Oct 2024. Boundary months excluded as potentially partial.
A10: =EDATE('Monthly Summary'!$A$30,5) -> 45748 | B10: =_xlfn.FORECAST.ETS(A10,'Monthly Summary'!$B$7:$B$29,'Monthly Summary'!$A$7:$A$29,0,1,1) -> 5.2034636 | C10: =MAX(0,ROUND(B10,0)) -> 5 | D10: =C10*$B$22 -> 2415
A11: =EDATE('Monthly Summary'!$A$30,6) -> 45778 | B11: =_xlfn.FORECAST.ETS(A11,'Monthly Summary'!$B$7:$B$29,'Monthly Summary'!$A$7:$A$29,0,1,1) -> 5.2445689 | C11: =MAX(0,ROUND(B11,0)) -> 5 | D11: =C11*$B$22 -> 2415 | F11: ETS seasonality
A12: =EDATE('Monthly Summary'!$A$30,7) -> 45809 | B12: =_xlfn.FORECAST.ETS(A12,'Monthly Summary'!$B$7:$B$29,'Monthly Summary'!$A$7:$A$29,0,1,1) -> 5.2856742 | C12: =MAX(0,ROUND(B12,0)) -> 5 | D12: =C12*$B$22 -> 2415 | F12: 0 (no seasonality). Fewer than two full annual cycles are available.
A13: =EDATE('Monthly Summary'!$A$30,8) -> 45839 | B13: =_xlfn.FORECAST.ETS(A13,'Monthly Summary'!$B$7:$B$29,'Monthly Summary'!$A$7:$A$29,0,1,1) -> 5.3267795 | C13: =MAX(0,ROUND(B13,0)) -> 5 | D13: =C13*$B$22 -> 2415
A14: =EDATE('Monthly Summary'!$A$30,9) -> 45870 | B14: =_xlfn.FORECAST.ETS(A14,'Monthly Summary'!$B$7:$B$29,'Monthly Summary'!$A$7:$A$29,0,1,1) -> 5.3678847 | C14: =MAX(0,ROUND(B14,0)) -> 5 | D14: =C14*$B$22 -> 2415 | F14: Attendance proxy
A15: =EDATE('Monthly Summary'!$A$30,10) -> 45901 | B15: =_xlfn.FORECAST.ETS(A15,'Monthly Summary'!$B$7:$B$29,'Monthly Summary'!$A$7:$A$29,0,1,1) -> 5.40899 | C15: =MAX(0,ROUND(B15,0)) -> 5 | D15: =C15*$B$22 -> 2415 | F15: Registration counts are used. Actual check-in attendance is not supplied.
A16: =EDATE('Monthly Summary'!$A$30,11) -> 45931 | B16: =_xlfn.FORECAST.ETS(A16,'Monthly Summary'!$B$7:$B$29,'Monthly Summary'!$A$7:$A$29,0,1,1) -> 5.4500953 | C16: =MAX(0,ROUND(B16,0)) -> 5 | D16: =C16*$B$22 -> 2415
A17: =EDATE('Monthly Summary'!$A$30,12) -> 45962 | B17: =_xlfn.FORECAST.ETS(A17,'Monthly Summary'!$B$7:$B$29,'Monthly Summary'!$A$7:$A$29,0,1,1) -> 5.4912006 | C17: =MAX(0,ROUND(B17,0)) -> 5 | D17: =C17*$B$22 -> 2415 | F17: Budget basis
F18: Marketing and operating costs apply once to the 12-month plan.
A19: 12-month planning total | B19: =SUM(B6:B17) -> 63.181459 | C19: =SUM(C6:C17) -> 60 | D19: =SUM(D6:D17) -> 28980
F20: Revenue basis
A21: Financial model | B21: Original budget | D21: Budget Challenge | F21: Ticket revenue only. No sponsorship or exchange rates added.
A22: Average ticket price (EUR) | B22: ='Monthly Summary'!D32 -> 483 | D22: ='Monthly Summary'!D32 -> 483
A23: Predicted attendance | B23: =$C$19 -> 60 | D23: =$C$19 -> 60 | F23: Goal Seek price
A24: Forecasted revenue (EUR) | B24: =B22*B23 -> 28980 | D24: =D22*D23 -> 28980 | F24: Set B33 to the target in B28 by changing B32. Challenge: D33 / D28 / D32.
A25: Marketing costs (EUR) | B25: =Assumptions!C4 -> 9000 | D25: =Assumptions!F4 -> 10000
A26: Operational costs (EUR) | B26: =Assumptions!C6 -> 4300 | D26: =Assumptions!F6 -> 25000 | F26: Goal Seek attendance
A27: Forecast profit (EUR) | B27: =B24-SUM(B25:B26) -> 15680 | D27: =D24-SUM(D25:D26) -> -6020 | F27: Set B37 to B28 by changing B36. Challenge: D37 / D28 / D36.
A28: Profit target (EUR) | B28: =IF(ISNUMBER(Assumptions!C2),Assumptions!C2,"Enter target") -> 45000 | D28: =IF(ISNUMBER(Assumptions!F2),Assumptions!F2,"Enter target") -> Enter target
A29: Gap to target (EUR) | B29: =IF(ISNUMBER(B28),B27-B28,"Enter target") -> -29320 | D29: =IF(ISNUMBER(D28),D27-D28,"Enter target") -> Enter target | F29: Rounding
F30: Price solution is unrounded. Round UP for a payable price. Attendees round UP.
A32: Goal Seek: price input (EUR) | B32: 971.66667 | D32: 483
A33: Profit at price input (EUR) | B33: =B32*B23-SUM(B25:B26) -> 45000 | D33: =D32*D23-SUM(D25:D26) -> -6020
A34: Required ticket price (EUR) | B34: =IF(ISNUMBER(B28),(B28+SUM(B25:B26))/B23,"Enter target") -> 971.66667 | D34: =IF(ISNUMBER(D28),(D28+SUM(D25:D26))/D23,"Enter target") -> Enter target
A36: Goal Seek: attendee input | B36: 120.70393 | D36: 100
A37: Profit at attendee input (EUR) | B37: =B36*B22-SUM(B25:B26) -> 45000 | D37: =D36*D22-SUM(D25:D26) -> 13300
A38: Minimum whole attendees | B38: =IF(ISNUMBER(B28),ROUNDUP((B28+SUM(B25:B26))/B22,0),"Enter target") -> 121 | D38: =IF(ISNUMBER(D28),ROUNDUP((D28+SUM(D25:D26))/D22,0),"Enter target") -> Enter target
A39: Profit at minimum attendees (EUR) | B39: =IF(ISNUMBER(B38),B38*B22-SUM(B25:B26),"Enter target") -> 45143 | D39: =IF(ISNUMBER(D38),D38*D22-SUM(D25:D26),"Enter target") -> Enter target

Sheet Monthly Summary
A1: Monthly registrations and ticket sales
A5: Registration month | B5: Registrations | C5: Ticket sales (EUR) | D5: Average ticket (EUR) | E5: Forecast training | F5: Month label
A6: 44866 | B6: =COUNTIFS(Attendees[Registration Date],">="&A6,Attendees[Registration Date],"<"&EDATE(A6,1)) -> 1 | C6: =SUMIFS(Attendees[Ticket Price (€)],Attendees[Registration Date],">="&A6,Attendees[Registration Date],"<"&EDATE(A6,1)) -> 450 | D6: =IF(B6=0,0,C6/B6) -> 450 | E6: Boundary excluded | F6: =TEXT(A6,"mmm yy") -> Nov 22
A7: 44896 | B7: =COUNTIFS(Attendees[Registration Date],">="&A7,Attendees[Registration Date],"<"&EDATE(A7,1)) -> 4 | C7: =SUMIFS(Attendees[Ticket Price (€)],Attendees[Registration Date],">="&A7,Attendees[Registration Date],"<"&EDATE(A7,1)) -> 1900 | D7: =IF(B7=0,0,C7/B7) -> 475 | E7: Included | F7: =TEXT(A7,"mmm yy") -> Dec 22
A8: 44927 | B8: =COUNTIFS(Attendees[Registration Date],">="&A8,Attendees[Registration Date],"<"&EDATE(A8,1)) -> 3 | C8: =SUMIFS(Attendees[Ticket Price (€)],Attendees[Registration Date],">="&A8,Attendees[Registration Date],"<"&EDATE(A8,1)) -> 1450 | D8: =IF(B8=0,0,C8/B8) -> 483.33333 | E8: Included | F8: =TEXT(A8,"mmm yy") -> Jan 23
A9: 44958 | B9: =COUNTIFS(Attendees[Registration Date],">="&A9,Attendees[Registration Date],"<"&EDATE(A9,1)) -> 8 | C9: =SUMIFS(Attendees[Ticket Price (€)],Attendees[Registration Date],">="&A9,Attendees[Registration Date],"<"&EDATE(A9,1)) -> 3900 | D9: =IF(B9=0,0,C9/B9) -> 487.5 | E9: Included | F9: =TEXT(A9,"mmm yy") -> Feb 23
A10: 44986 | B10: =COUNTIFS(Attendees[Registration Date],">="&A10,Attendees[Registration Date],"<"&EDATE(A10,1)) -> 1 | C10: =SUMIFS(Attendees[Ticket Price (€)],Attendees[Registration Date],">="&A10,Attendees[Registration Date],"<"&EDATE(A10,1)) -> 450 | D10: =IF(B10=0,0,C10/B10) -> 450 | E10: Included | F10: =TEXT(A10,"mmm yy") -> Mar 23
A11: 45017 | B11: =COUNTIFS(Attendees[Registration Date],">="&A11,Attendees[Registration Date],"<"&EDATE(A11,1)) -> 6 | C11: =SUMIFS(Attendees[Ticket Price (€)],Attendees[Registration Date],">="&A11,Attendees[Registration Date],"<"&EDATE(A11,1)) -> 2900 | D11: =IF(B11=0,0,C11/B11) -> 483.33333 | E11: Included | F11: =TEXT(A11,"mmm yy") -> Apr 23
A12: 45047 | B12: =COUNTIFS(Attendees[Registration Date],">="&A12,Attendees[Registration Date],"<"&EDATE(A12,1)) -> 3 | C12: =SUMIFS(Attendees[Ticket Price (€)],Attendees[Registration Date],">="&A12,Attendees[Registration Date],"<"&EDATE(A12,1)) -> 1450 | D12: =IF(B12=0,0,C12/B12) -> 483.33333 | E12: Included | F12: =TEXT(A12,"mmm yy") -> May 23
A13: 45078 | B13: =COUNTIFS(Attendees[Registration Date],">="&A13,Attendees[Registration Date],"<"&EDATE(A13,1)) -> 2 | C13: =SUMIFS(Attendees[Ticket Price (€)],Attendees[Registration Date],">="&A13,Attendees[Registration Date],"<"&EDATE(A13,1)) -> 1000 | D13: =IF(B13=0,0,C13/B13) -> 500 | E13: Included | F13: =TEXT(A13,"mmm yy") -> Jun 23
A14: 45108 | B14: =COUNTIFS(Attendees[Registration Date],">="&A14,Attendees[Registration Date],"<"&EDATE(A14,1)) -> 5 | C14: =SUMIFS(Attendees[Ticket Price (€)],Attendees[Registration Date],">="&A14,Attendees[Registration Date],"<"&EDATE(A14,1)) -> 2600 | D14: =IF(B14=0,0,C14/B14) -> 520 | E14: Included | F14: =TEXT(A14,"mmm yy") -> Jul 23
A15: 45139 | B15: =COUNTIFS(Attendees[Registration Date],">="&A15,Attendees[Registration Date],"<"&EDATE(A15,1)) -> 3 | C15: =SUMIFS(Attendees[Ticket Price (€)],Attendees[Registration Date],">="&A15,Attendees[Registration Date],"<"&EDATE(A15,1)) -> 1450 | D15: =IF(B15=0,0,C15/B15) -> 483.33333 | E15: Included | F15: =TEXT(A15,"mmm yy") -> Aug 23
A16: 45170 | B16: =COUNTIFS(Attendees[Registration Date],">="&A16,Attendees[Registration Date],"<"&EDATE(A16,1)) -> 3 | C16: =SUMIFS(Attendees[Ticket Price (€)],Attendees[Registration Date],">="&A16,Attendees[Registration Date],"<"&EDATE(A16,1)) -> 1450 | D16: =IF(B16=0,0,C16/B16) -> 483.33333 | E16: Included | F16: =TEXT(A16,"mmm yy") -> Sep 23
A17: 45200 | B17: =COUNTIFS(Attendees[Registration Date],">="&A17,Attendees[Registration Date],"<"&EDATE(A17,1)) -> 4 | C17: =SUMIFS(Attendees[Ticket Price (€)],Attendees[Registration Date],">="&A17,Attendees[Registration Date],"<"&EDATE(A17,1)) -> 1750 | D17: =IF(B17=0,0,C17/B17) -> 437.5 | E17: Included | F17: =TEXT(A17,"mmm yy") -> Oct 23
... A30: 45597 | B30: =COUNTIFS(Attendees[Registration Date],">="&A30,Attendees[Registration Date],"<"&EDATE(A30,1)) -> 2 | C30: =SUMIFS(Attendees[Ticket Price (€)],Attendees[Registration Date],">="&A30,Attendees[Registration Date],"<"&EDATE(A30,1)) -> 1000 | D30: =IF(B30=0,0,C30/B30) -> 500 | E30: Boundary excluded | F30: =TEXT(A30,"mmm yy") -> Nov 24
A32: Historical total | B32: =SUM(B6:B30) -> 100 | C32: =SUM(C6:C30) -> 48300 | D32: =C32/B32 -> 483

Sheet Attendee Management
A1: Attendee management
A5: Attendee ID
A6: Name
A7: Email
A8: Phone Number
A9: Attendance Type
A10: Session Preference
A11: Ticket Price (€)
A12: Registration Date
A13: Dietary Preference | B13: Not provided
A16: VBA setup is required to activate the management buttons.
A18: A commented VBA module and UserForm setup code are supplied separately.
A20: Edit Database directly and use Data > Refresh All until VBA is installed.

Sheet Database
A1: Attendee ID | B1: Name | C1: Email | D1: Phone Number | E1: Attendance Type | F1: Session Preference | G1: Ticket Price (€) | H1: Registration Date | I1: Dietary Preference | J1: Registration Month
A2: A001 | B2: Participant 1 | C2: Participant1@example.com | D2: 555-0001 | E2: Online | F2: Data Analytics | G2: 450 | H2: 44878 | I2: Not provided | J2: =DATE(YEAR(Attendees[[#This Row],[Registration Date]]),MONTH(Attendees[[#This Row],[Registration Date]]),1) -> 44866
A3: A002 | B3: Participant 2 | C3: Participant2@example.com | D3: 555-0002 | E3: In-Person | F3: Data Analytics | G3: 450 | H3: 44909 | I3: Not provided | J3: =DATE(YEAR(Attendees[[#This Row],[Registration Date]]),MONTH(Attendees[[#This Row],[Registration Date]]),1) -> 44896
A4: A003 | B4: Participant 3 | C4: Participant3@example.com | D4: 555-0003 | E4: Online | F4: Artificial Intelligence | G4: 700 | H4: 44915 | I4: Not provided | J4: =DATE(YEAR(Attendees[[#This Row],[Registration Date]]),MONTH(Attendees[[#This Row],[Registration Date]]),1) -> 44896
A5: A004 | B5: Participant 4 | C5: Participant4@example.com | D5: 555-0004 | E5: In-Person | F5: Cybersecurity | G5: 300 | H5: 44921 | I5: Not provided | J5: =DATE(YEAR(Attendees[[#This Row],[Registration Date]]),MONTH(Attendees[[#This Row],[Registration Date]]),1) -> 44896
A6: A005 | B6: Participant 5 | C6: Participant5@example.com | D6: 555-0005 | E6: Online | F6: Data Analytics | G6: 450 | H6: 44926 | I6: Not provided | J6: =DATE(YEAR(Attendees[[#This Row],[Registration Date]]),MONTH(Attendees[[#This Row],[Registration Date]]),1) -> 44896
A7: A006 | B7: Participant 6 | C7: Participant6@example.com | D7: 555-0006 | E7: In-Person | F7: Artificial Intelligence | G7: 700 | H7: 44937 | I7: Not provided | J7: =DATE(YEAR(Attendees[[#This Row],[Registration Date]]),MONTH(Attendees[[#This Row],[Registration Date]]),1) -> 44927
A8: A007 | B8: Participant 7 | C8: Participant7@example.com | D8: 555-0007 | E8: Online | F8: Cybersecurity | G8: 300 | H8: 44941 | I8: Not provided | J8: =DATE(YEAR(Attendees[[#This Row],[Registration Date]]),MONTH(Attendees[[#This Row],[Registration Date]]),1) -> 44927
A9: A008 | B9: Participant 8 | C9: Participant8@example.com | D9: 555-0008 | E9: In-Person | F9: Data Analytics | G9: 450 | H9: 44943 | I9: Not provided | J9: =DATE(YEAR(Attendees[[#This Row],[Registration Date]]),MONTH(Attendees[[#This Row],[Registration Date]]),1) -> 44927
A10: A009 | B10: Participant 9 | C10: Participant9@example.com | D10: 555-0009 | E10: Online | F10: Artificial Intelligence | G10: 700 | H10: 44962 | I10: Not provided | J10: =DATE(YEAR(Attendees[[#This Row],[Registration Date]]),MONTH(Attendees[[#This Row],[Registration Date]]),1) -> 44958
A11: A010 | B11: Participant 10 | C11: Participant10@example.com | D11: 555-0010 | E11: In-Person | F11: Cybersecurity | G11: 300 | H11: 44966 | I11: Not provided | J11: =DATE(YEAR(Attendees[[#This Row],[Registration Date]]),MONTH(Attendees[[#This Row],[Registration Date]]),1) -> 44958
A12: A011 | B12: Participant 11 | C12: Participant11@example.com | D12: 555-0011 | E12: Online | F12: Data Analytics | G12: 450 | H12: 44971 | I12: Not provided | J12: =DATE(YEAR(Attendees[[#This Row],[Registration Date]]),MONTH(Attendees[[#This Row],[Registration Date]]),1) -> 44958
A13: A012 | B13: Participant 12 | C13: Participant12@example.com | D13: 555-0012 | E13: In-Person | F13: Artificial Intelligence | G13: 700 | H13: 44975 | I13: Not provided | J13: =DATE(YEAR(Attendees[[#This Row],[Registration Date]]),MONTH(Attendees[[#This Row],[Registration Date]]),1) -> 44958
... A101: A100 | B101: Participant 100 | C101: Participant100@example.com | D101: 555-0100 | E101: In-Person | F101: Cybersecurity | G101: 300 | H101: 45605 | I101: Not provided | J101: =DATE(YEAR(Attendees[[#This Row],[Registration Date]]),MONTH(Attendees[[#This Row],[Registration Date]]),1) -> 45597

Sheet Original Data
B1: Name | C1: Email | D1: Phone Number | E1: Attendance Type | F1: Session Preference | G1: Ticket Price (€) | H1: Registration Date
A2: A001 | B2: Participant 1 | C2: Participant1@example.com | D2: 555-0001 | E2: Online | F2: Data Analytics | G2: 450 | H2: 44878
A3: A002 | B3: Participant 2 | C3: Participant2@example.com | D3: 555-0002 | E3: In-Person | F3: Data Analytics | G3: 450 | H3: 44909
A4: A003 | B4: Participant 3 | C4: Participant3@example.com | D4: 555-0003 | E4: Online | F4: Artificial Intelligence | G4: 700 | H4: 44915
A5: A004 | B5: Participant 4 | C5: Participant4@example.com | D5: 555-0004 | E5: In-Person | F5: Cybersecurity | G5: 300 | H5: 44921
A6: A005 | B6: Participant 5 | C6: Participant5@example.com | D6: 555-0005 | E6: Online | F6: Data Analytics | G6: 450 | H6: 44926
A7: A006 | B7: Participant 6 | C7: Participant6@example.com | D7: 555-0006 | E7: In-Person | F7: Artificial Intelligence | G7: 700 | H7: 44937
A8: A007 | B8: Participant 7 | C8: Participant7@example.com | D8: 555-0007 | E8: Online | F8: Cybersecurity | G8: 300 | H8: 44941
A9: A008 | B9: Participant 8 | C9: Participant8@example.com | D9: 555-0008 | E9: In-Person | F9: Data Analytics | G9: 450 | H9: 44943
A10: A009 | B10: Participant 9 | C10: Participant9@example.com | D10: 555-0009 | E10: Online | F10: Artificial Intelligence | G10: 700 | H10: 44962
A11: A010 | B11: Participant 10 | C11: Participant10@example.com | D11: 555-0010 | E11: In-Person | F11: Cybersecurity | G11: 300 | H11: 44966
A12: A011 | B12: Participant 11 | C12: Participant11@example.com | D12: 555-0011 | E12: Online | F12: Data Analytics | G12: 450 | H12: 44971
A13: A012 | B13: Participant 12 | C13: Participant12@example.com | D13: 555-0012 | E13: In-Person | F13: Artificial Intelligence | G13: 700 | H13: 44975
... A101: A100 | B101: Participant 100 | C101: Participant100@example.com | D101: 555-0100 | E101: In-Person | F101: Cybersecurity | G101: 300 | H101: 45605

Sheet ReadMe
A1: Workbook guide and changes
A5: Source | B5: Tech Innovators Summit dataset. Original Data preserves the supplied eight columns and 100 records. Original assumptions remain in Assumptions!C2/C4/C6.
A7: Preparation | B7: Added Attendee ID header, Dietary Preference (Not provided), registration-month helper, data validation and an expandable Attendees table.
A9: Monthly summaries | B9: All source months are included. A zero means no registrations in the supplied file for that month, not proof of full operational coverage.
A11: Forecast | B11: ETS without seasonality uses the 23 interior months. Twelve future months are a planning assumption. Registration dates are not event dates.
A13: Budget Challenge | B13: Marketing EUR 10,000; operations EUR 25,000. Assignment target “EUR 100,00” is ambiguous. Confirm and enter Assumptions!F2.
A15: Pricing alternatives | B15: Required price holds forecast attendance fixed. Minimum attendees holds the historic average price fixed. These are alternative strategies, not simultaneous assumptions.
A17: Interactive dashboards | B17: Each dashboard has separate attendance/session slicers and registration-date timeline. All three historical charts and historical KPIs share those filters.
A19: Refresh | B19: After editing or adding Database rows, use Data > Refresh All. The supplied RefreshDashboard macro refreshes pivots and calculations once installed.
A21: VBA limitation | B21: Excel denies programmatic VBA-project access. XLSX has no embedded macros. Supplied VBA covers attendee actions and refresh, but execution and UserForm setup remain untested.
A23: Attendee form | B23: The worksheet form can be used after importing the module. Optional setup code builds the requested AttendeeForm with TextBoxes, ComboBoxes, OptionButtons and a dietary ListBox.
A25: Preservation | B25: No unsupported exchange rate, sponsor revenue, dietary selections, event dates or row-level marketing costs were fabricated.
A27: Forecast updates | B27: Monthly history, trend charts and forecast windows use the source period. For new months, extend Monthly Summary, Dashboard Data, line-chart ranges and forecast references. Unhide support sheets via Home > Format > Hide & Unhide.
A29: Currency | B29: All financial values are EUR. Target and costs are budget inputs; there is no source evidence of actual historical event expenses.

Sheet Dashboard Data
A1: Filtered dashboard chart data
A5: Session | B5: Revenue (EUR) | C5: Attendees | H5: Session | I5: Revenue (EUR) | J5: Attendees
A6: Data Analytics | B6: =IFERROR(GETPIVOTDATA("Ticket revenue",'Pivot Support'!$A$1,"Session Preference",A6),0) -> 15300 | C6: =IFERROR(GETPIVOTDATA("Attendee count",'Pivot Support'!$A$1,"Session Preference",A6),0) -> 34 | H6: Data Analytics | I6: =IFERROR(GETPIVOTDATA("Ticket revenue",'Pivot Support'!$K$1,"Session Preference",H6),0) -> 15300 | J6: =IFERROR(GETPIVOTDATA("Attendee count",'Pivot Support'!$K$1,"Session Preference",H6),0) -> 34
A7: Artificial Intelligence | B7: =IFERROR(GETPIVOTDATA("Ticket revenue",'Pivot Support'!$A$1,"Session Preference",A7),0) -> 23100 | C7: =IFERROR(GETPIVOTDATA("Attendee count",'Pivot Support'!$A$1,"Session Preference",A7),0) -> 33 | H7: Artificial Intelligence | I7: =IFERROR(GETPIVOTDATA("Ticket revenue",'Pivot Support'!$K$1,"Session Preference",H7),0) -> 23100 | J7: =IFERROR(GETPIVOTDATA("Attendee count",'Pivot Support'!$K$1,"Session Preference",H7),0) -> 33
A8: Cybersecurity | B8: =IFERROR(GETPIVOTDATA("Ticket revenue",'Pivot Support'!$A$1,"Session Preference",A8),0) -> 9900 | C8: =IFERROR(GETPIVOTDATA("Attendee count",'Pivot Support'!$A$1,"Session Preference",A8),0) -> 33 | H8: Cybersecurity | I8: =IFERROR(GETPIVOTDATA("Ticket revenue",'Pivot Support'!$K$1,"Session Preference",H8),0) -> 9900 | J8: =IFERROR(GETPIVOTDATA("Attendee count",'Pivot Support'!$K$1,"Session Preference",H8),0) -> 33
A11: Attendance type | B11: Attendees | H11: Attendance type | I11: Attendees
A12: Online | B12: =IFERROR(GETPIVOTDATA("Attendee count",'Pivot Support'!$A$12,"Attendance Type",A12),0) -> 50 | H12: Online | I12: =IFERROR(GETPIVOTDATA("Attendee count",'Pivot Support'!$K$12,"Attendance Type",H12),0) -> 50
A13: In-Person | B13: =IFERROR(GETPIVOTDATA("Attendee count",'Pivot Support'!$A$12,"Attendance Type",A13),0) -> 50 | H13: In-Person | I13: =IFERROR(GETPIVOTDATA("Attendee count",'Pivot Support'!$K$12,"Attendance Type",H13),0) -> 50
A16: Month | B16: Registrations | C16: Month date | H16: Month | I16: Registrations | J16: Month date
A17: =TEXT(C17,"mmm yy") -> Nov 22 | B17: =IFERROR(GETPIVOTDATA("Attendee count",'Pivot Support'!$A$24,"Registration Month",C17),0) -> 1 | C17: 44866 | H17: =TEXT(J17,"mmm yy") -> Nov 22 | I17: =IFERROR(GETPIVOTDATA("Attendee count",'Pivot Support'!$K$24,"Registration Month",J17),0) -> 1 | J17: 44866
A18: =TEXT(C18,"mmm yy") -> Dec 22 | B18: =IFERROR(GETPIVOTDATA("Attendee count",'Pivot Support'!$A$24,"Registration Month",C18),0) -> 4 | C18: 44896 | H18: =TEXT(J18,"mmm yy") -> Dec 22 | I18: =IFERROR(GETPIVOTDATA("Attendee count",'Pivot Support'!$K$24,"Registration Month",J18),0) -> 4 | J18: 44896
A19: =TEXT(C19,"mmm yy") -> Jan 23 | B19: =IFERROR(GETPIVOTDATA("Attendee count",'Pivot Support'!$A$24,"Registration Month",C19),0) -> 3 | C19: 44927 | H19: =TEXT(J19,"mmm yy") -> Jan 23 | I19: =IFERROR(GETPIVOTDATA("Attendee count",'Pivot Support'!$K$24,"Registration Month",J19),0) -> 3 | J19: 44927
A20: =TEXT(C20,"mmm yy") -> Feb 23 | B20: =IFERROR(GETPIVOTDATA("Attendee count",'Pivot Support'!$A$24,"Registration Month",C20),0) -> 8 | C20: 44958 | H20: =TEXT(J20,"mmm yy") -> Feb 23 | I20: =IFERROR(GETPIVOTDATA("Attendee count",'Pivot Support'!$K$24,"Registration Month",J20),0) -> 8 | J20: 44958
A21: =TEXT(C21,"mmm yy") -> Mar 23 | B21: =IFERROR(GETPIVOTDATA("Attendee count",'Pivot Support'!$A$24,"Registration Month",C21),0) -> 1 | C21: 44986 | H21: =TEXT(J21,"mmm yy") -> Mar 23 | I21: =IFERROR(GETPIVOTDATA("Attendee count",'Pivot Support'!$K$24,"Registration Month",J21),0) -> 1 | J21: 44986
A22: =TEXT(C22,"mmm yy") -> Apr 23 | B22: =IFERROR(GETPIVOTDATA("Attendee count",'Pivot Support'!$A$24,"Registration Month",C22),0) -> 6 | C22: 45017 | H22: =TEXT(J22,"mmm yy") -> Apr 23 | I22: =IFERROR(GETPIVOTDATA("Attendee count",'Pivot Support'!$K$24,"Registration Month",J22),0) -> 6 | J22: 45017
A23: =TEXT(C23,"mmm yy") -> May 23 | B23: =IFERROR(GETPIVOTDATA("Attendee count",'Pivot Support'!$A$24,"Registration Month",C23),0) -> 3 | C23: 45047 | H23: =TEXT(J23,"mmm yy") -> May 23 | I23: =IFERROR(GETPIVOTDATA("Attendee count",'Pivot Support'!$K$24,"Registration Month",J23),0) -> 3 | J23: 45047
A24: =TEXT(C24,"mmm yy") -> Jun 23 | B24: =IFERROR(GETPIVOTDATA("Attendee count",'Pivot Support'!$A$24,"Registration Month",C24),0) -> 2 | C24: 45078 | H24: =TEXT(J24,"mmm yy") -> Jun 23 | I24: =IFERROR(GETPIVOTDATA("Attendee count",'Pivot Support'!$K$24,"Registration Month",J24),0) -> 2 | J24: 45078
A25: =TEXT(C25,"mmm yy") -> Jul 23 | B25: =IFERROR(GETPIVOTDATA("Attendee count",'Pivot Support'!$A$24,"Registration Month",C25),0) -> 5 | C25: 45108 | H25: =TEXT(J25,"mmm yy") -> Jul 23 | I25: =IFERROR(GETPIVOTDATA("Attendee count",'Pivot Support'!$K$24,"Registration Month",J25),0) -> 5 | J25: 45108
A26: =TEXT(C26,"mmm yy") -> Aug 23 | B26: =IFERROR(GETPIVOTDATA("Attendee count",'Pivot Support'!$A$24,"Registration Month",C26),0) -> 3 | C26: 45139 | H26: =TEXT(J26,"mmm yy") -> Aug 23 | I26: =IFERROR(GETPIVOTDATA("Attendee count",'Pivot Support'!$K$24,"Registration Month",J26),0) -> 3 | J26: 45139
A27: =TEXT(C27,"mmm yy") -> Sep 23 | B27: =IFERROR(GETPIVOTDATA("Attendee count",'Pivot Support'!$A$24,"Registration Month",C27),0) -> 3 | C27: 45170 | H27: =TEXT(J27,"mmm yy") -> Sep 23 | I27: =IFERROR(GETPIVOTDATA("Attendee count",'Pivot Support'!$K$24,"Registration Month",J27),0) -> 3 | J27: 45170
A28: =TEXT(C28,"mmm yy") -> Oct 23 | B28: =IFERROR(GETPIVOTDATA("Attendee count",'Pivot Support'!$A$24,"Registration Month",C28),0) -> 4 | C28: 45200 | H28: =TEXT(J28,"mmm yy") -> Oct 23 | I28: =IFERROR(GETPIVOTDATA("Attendee count",'Pivot Support'!$K$24,"Registration Month",J28),0) -> 4 | J28: 45200
... A41: =TEXT(C41,"mmm yy") -> Nov 24 | B41: =IFERROR(GETPIVOTDATA("Attendee count",'Pivot Support'!$A$24,"Registration Month",C41),0) -> 2 | C41: 45597 | H41: =TEXT(J41,"mmm yy") -> Nov 24 | I41: =IFERROR(GETPIVOTDATA("Attendee count",'Pivot Support'!$K$24,"Registration Month",J41),0) -> 2 | J41: 45597

Sheet Pivot Support
A1: Session Preference | B1: Attendee count | C1: Ticket revenue | K1: Session Preference | L1: Attendee count | M1: Ticket revenue
A2: Artificial Intelligence | B2: 33 | C2: 23100 | K2: Artificial Intelligence | L2: 33 | M2: 23100
A3: Cybersecurity | B3: 33 | C3: 9900 | K3: Cybersecurity | L3: 33 | M3: 9900
A4: Data Analytics | B4: 34 | C4: 15300 | K4: Data Analytics | L4: 34 | M4: 15300
A5: Grand Total | B5: 100 | C5: 48300 | K5: Grand Total | L5: 100 | M5: 48300
A12: Attendance Type | B12: Attendee count | C12: Ticket revenue | K12: Attendance Type | L12: Attendee count | M12: Ticket revenue
A13: In-Person | B13: 50 | C13: 23950 | K13: In-Person | L13: 50 | M13: 23950
A14: Online | B14: 50 | C14: 24350 | K14: Online | L14: 50 | M14: 24350
A15: Grand Total | B15: 100 | C15: 48300 | K15: Grand Total | L15: 100 | M15: 48300
A24: Registration Month | B24: Attendee count | C24: Ticket revenue | K24: Registration Month | L24: Attendee count | M24: Ticket revenue
A25: 44866 | B25: 1 | C25: 450 | K25: 44866 | L25: 1 | M25: 450
A26: 44896 | B26: 4 | C26: 1900 | K26: 44896 | L26: 4 | M26: 1900
A27: 44927 | B27: 3 | C27: 1450 | K27: 44927 | L27: 3 | M27: 1450
A28: 44958 | B28: 8 | C28: 3900 | K28: 44958 | L28: 8 | M28: 3900
A29: 44986 | B29: 1 | C29: 450 | K29: 44986 | L29: 1 | M29: 450
A30: 45017 | B30: 6 | C30: 2900 | K30: 45017 | L30: 6 | M30: 2900
A31: 45047 | B31: 3 | C31: 1450 | K31: 45047 | L31: 3 | M31: 1450
A32: 45078 | B32: 2 | C32: 1000 | K32: 45078 | L32: 2 | M32: 1000
A33: 45108 | B33: 5 | C33: 2600 | K33: 45108 | L33: 5 | M33: 2600
A34: 45139 | B34: 3 | C34: 1450 | K34: 45139 | L34: 3 | M34: 1450
A35: 45170 | B35: 3 | C35: 1450 | K35: 45170 | L35: 3 | M35: 1450
A36: 45200 | B36: 4 | C36: 1750 | K36: 45200 | L36: 4 | M36: 1750
... A49: 45597 | B49: 2 | C49: 1000 | K49: 45597 | L49: 2 | M49: 1000
A50: Grand Total | B50: 100 | C50: 48300 | K50: Grand Total | L50: 100 | M50: 48300
